hirsh/__init__.py
hirsh/__main__.py
hirsh/config.py
hirsh/daemon.py
hirsh/entities/__init__.py
hirsh/entities/base.py
hirsh/entities/events.py
hirsh/entities/logs.py
hirsh/logging.py
hirsh/py.typed
hirsh/repositories/__init__.py
hirsh/repositories/database.py
hirsh/repositories/events.py
hirsh/repositories/logs.py
hirsh/runtime.py
hirsh/services/__init__.py
hirsh/services/events.py
hirsh/services/monitors.py
hirsh/services/network.py
hirsh/services/notifiers.py
hirsh-0.0.2.dist-info/LICENSE
hirsh-0.0.2.dist-info/WHEEL
hirsh-0.0.2.dist-info/METADATA
hirsh-0.0.2.dist-info/RECORD
