Metadata-Version: 2.1
Name: hirsh
Version: 0.0.2
Summary: Resilient monitoring system that detects utility outages in unreliable environments (e.g. IoT, RaspberryPi, etc)
License: Apache-2.0
Author: Roman Glushko
Author-email: roman.glushko.m@gmail.com
Requires-Python: >=3.9,<4.0
Classifier: Framework :: AsyncIO
Classifier: Intended Audience :: Information Technology
Classifier: Intended Audience :: System Administrators
Classifier: License :: OSI Approved :: Apache Software License
Classifier: Operating System :: OS Independent
Classifier: Programming Language :: Python :: 3
Classifier: Programming Language :: Python :: 3.9
Classifier: Programming Language :: Python :: 3.10
Classifier: Programming Language :: Python :: 3
Classifier: Programming Language :: Python :: 3 :: Only
Classifier: Programming Language :: Python :: 3.9
Classifier: Topic :: Internet
Classifier: Topic :: Software Development
Classifier: Typing :: Typed
Requires-Dist: PyYAML (>=6.0,<7.0)
Requires-Dist: SQLAlchemy[asyncio,mypy] (>=1.4.44,<2.0.0)
Requires-Dist: aiogram (>=2.23.1,<3.0.0)
Requires-Dist: aiosqlite (>=0.17.0,<0.18.0)
Requires-Dist: dependency-injector (>=4.40.0,<5.0.0)
Requires-Dist: pydantic (>=1.10.2,<2.0.0)
Requires-Dist: typer (>=0.7.0,<0.8.0)
Requires-Dist: uvloop (>=0.17.0,<0.18.0)
